{
  "hash": "6094107e119e5f7a8101a3156359039eb04970d7878dab1edee4d02c413524ad",
  "nome": "TRE_134973db04f3",
  "indexado_em": "2026-05-04T15:56:51.342543",
  "n_chunks": 43,
  "type": "ruling",
  "year": "2026",
  "court": "tre",
  "source": "ITIJ",
  "url": "https://www.dgsi.pt/jtre.nsf/134973db04f39bf2802579bf005f080b/f0a7ca59f58a574f80258d99003c9e34?OpenDocument",
  "tribunal_id": "tre",
  "processo": "111/25.0T8FAR.E1",
  "relator": "LUÍS JARDIM",
  "descritores": "PERÍODO EXPERIMENTAL, NULIDADE, SEGURANÇA NO EMPREGO, DESPEDIMENTO"
}